{
 "route": "925",
 "route_type": "General",
 "gtfs_note": "before = GTFS planned schedule; each route_id is a distinct trip-pattern (variant); frequency = number of distinct planned trips (trip_ids) on it. PRE-MERGE resolution: tag each variant, do NOT merge.",
 "n_variants": 1,
 "direction_groups": {
  "법원 순환": [
   "BR_TAGO_USB193109253"
  ]
 },
 "variants": [
  {
   "route_id": "BR_TAGO_USB193109253",
   "route_name": "925(법원 순환)",
   "dir_label": "법원 순환",
   "n_stops": 57,
   "frequency": 60,
   "is_loop": true,
   "first_raw": "법원",
   "last_raw": "법원",
   "first_norm": "법원",
   "last_norm": "법원",
   "stop_names_raw": [
    "법원",
    "천호탕앞",
    "서강파크앞",
    "옥동현대아파트앞",
    "신정중학교앞",
    "대륙2차현대아파트앞",
    "도성가든후문",
    "푸른아파트앞",
    "우주가든앞",
    "은월아파트앞",
    "축협앞",
    "남부신협앞",
    "신정시장앞",
    "한국케이블방송앞",
    "남부교회",
    "신정3동주민센터입구",
    "강남고등학교",
    "남경노블랜드",
    "울산병원",
    "극동스타클래스",
    "남구문화원앞",
    "남울산우체국",
    "삼산현대아파트앞",
    "남부소방서앞",
    "남구보건소앞",
    "대현중학교",
    "현대백화점",
    "시외고속버스터미널/신세계안과의원",
    "농수산물도매시장앞",
    "공구월드앞",
    "시외고속버스터미널/신세계안과의원",
    "현대백화점정문",
    "대현중학교",
    "남구보건소앞",
    "남부소방서앞",
    "삼산현대아파트앞",
    "남울산우체국",
    "남구문화원앞",
    "세이브존",
    "남경노블랜드",
    "강남고등학교",
    "신정3동주민센터입구",
    "남부교회",
    "한국케이블공사앞",
    "신정시장앞",
    "남부신협앞",
    "축협앞",
    "신한로얄멤버스아파트",
    "은월아파트앞",
    "우주가든앞",
    "푸른아파트앞",
    "도성가든후문",
    "대륙2차현대아파트앞",
    "신정중학교앞",
    "옥동현대아파트앞",
    "서강파크앞",
    "법원"
   ]
  }
 ],
 "pairs": []
}